{
  "info": {
    "_dirName": "info",
    "_dirType": "sub",
    "icon": {
      "_dirName": "icon",
      "_dirType": "canvas",
      "_width": 28,
      "_height": 24,
      "_image": "iVBORw0KGgoAAAANSUhEUgAAABwAAAAYCAYAAADpnJ2CAAAAAXNSR0IArs4c6QAAAARnQU1BAACxjwv8YQUAAAAJcEhZcwAADsMAAA7DAcdvqGQAAAE7SURBVEhLvVILccMwFDOFUAiFUQiFUSiFUCiFURiFURiWUtDu5Syf/PwS2\u002B023enq2Po4r0npF7EsC4x\u002B/8/x76UvF3JUMyMb1VU4K4j2PEY0FaYNAYYzhoUdDOUMiSZwmaeHz3wkkd4/F/CAJgAPAF8A7lEQMaJvvFqWjcWc18e\u002BN47qK5\u002B/iZhvagawXxR29WXN13fmHcC3mC3M9suoZvRk1ZwDmrFY2LZtXPvCQ5/Pix7AZ6SP3tCX8aYPCzWu61oCuBfpude8oSKX0mw3rcxWpgH2fKUPSxS5kGauj1\u002Bev6IPIeNtxuK1hln9KXR0un1Gp9ezIVC8Ct8ytwnSY/6wnCUMfk8p3TJ34T2gnivNazmWWZWyjEU\u002B/KNDfwFe4rKw92ZnpJbhJMfaHan/35T63yjVx4Lmw/kBF11WxgLtLm4AAAAASUVORK5CYII=",
      "origin": {
        "_dirName": "origin",
        "_dirType": "vector",
        "_x": -2,
        "_y": 24
      }
    },
    "iconRaw": {
      "_dirName": "iconRaw",
      "_dirType": "canvas",
      "_width": 27,
      "_height": 19,
      "_image": "iVBORw0KGgoAAAANSUhEUgAAABsAAAATCAYAAABhh3Y4AAAAAXNSR0IArs4c6QAAAARnQU1BAACxjwv8YQUAAAAJcEhZcwAADsMAAA7DAcdvqGQAAADrSURBVEhLvZKBDcMgDASzAitkFmbpClmhs3SFrtBZssJXRtgyxiSmafsSKjH3frC6LF9USgm0bP2n\u002BmvgpTAez8yYopxo1NyrWUUY0RQ8UKhHCArotM8pMKlhP33wyR/C4\u002B13U2QDgB3AE8Dda8KK8I1XB1WTGOu\u002B1G1glBefvYEy3rQRwHYQdsqXPT/ZGDcAL2WkRlSX8czwvOwIu1FQo5wz721Y4eu58AAeHm9fZoP4hjs1pLWuq5i55vFca16mVQPZSDdsjBSkzfR9xHcBWjWMjbwvv3x\u002Bhe\u002BkRtqNwrKkWd6VHpc98xTh31AGMDHO5UJUAAAAAElFTkSuQmCC",
      "origin": {
        "_dirName": "origin",
        "_dirType": "vector",
        "_x": -2,
        "_y": 24
      }
    },
    "islot": {
      "_dirName": "islot",
      "_dirType": "String",
      "_value": "Ay"
    },
    "vslot": {
      "_dirName": "vslot",
      "_dirType": "String",
      "_value": "Ay"
    },
    "reqJob": {
      "_dirName": "reqJob",
      "_dirType": "Int",
      "_value": 0
    },
    "reqLevel": {
      "_dirName": "reqLevel",
      "_dirType": "Int",
      "_value": 0
    },
    "reqSTR": {
      "_dirName": "reqSTR",
      "_dirType": "Int",
      "_value": 0
    },
    "reqDEX": {
      "_dirName": "reqDEX",
      "_dirType": "Int",
      "_value": 0
    },
    "reqINT": {
      "_dirName": "reqINT",
      "_dirType": "Int",
      "_value": 0
    },
    "reqLUK": {
      "_dirName": "reqLUK",
      "_dirType": "Int",
      "_value": 0
    },
    "cash": {
      "_dirName": "cash",
      "_dirType": "Int",
      "_value": 1
    }
  },
  "default": {
    "_dirName": "default",
    "_dirType": "sub",
    "default": {
      "_dirName": "default",
      "_dirType": "canvas",
      "_width": 15,
      "_height": 6,
      "_image": "iVBORw0KGgoAAAANSUhEUgAAAA8AAAAGCAYAAAAc2cSCAAAAAXNSR0IArs4c6QAAAARnQU1BAACxjwv8YQUAAAAJcEhZcwAADsMAAA7DAcdvqGQAAABhSURBVChTfZBRDYAwDAUnDgtYmAUsYAELWMDCLEzLkZe0ZSyFS/qz3ttLWsoDNn\u002BkDsAC1GxpuLOOjh4rsAMn0IaGGHM28w7/QIsIAj1plxNBuXP7V9CRo4Irc9JjTLycG/tBcG5R7RpWAAAAAElFTkSuQmCC",
      "origin": {
        "_dirName": "origin",
        "_dirType": "vector",
        "_x": 9,
        "_y": -13
      },
      "map": {
        "_dirName": "map",
        "_dirType": "sub",
        "brow": {
          "_dirName": "brow",
          "_dirType": "vector",
          "_x": 0,
          "_y": 0
        }
      },
      "z": {
        "_dirName": "z",
        "_dirType": "String",
        "_value": "accessoryEye"
      }
    }
  },
  "walk1": {
    "_dirName": "walk1",
    "_dirType": "sub",
    "0": {
      "_dirName": "0",
      "_dirType": "sub",
      "default": {
        "_dirName": "default",
        "_dirType": "uol",
        "_value": "../../default/default"
      }
    },
    "1": {
      "_dirName": "1",
      "_dirType": "sub",
      "default": {
        "_dirName": "default",
        "_dirType": "uol",
        "_value": "../../default/default"
      }
    },
    "2": {
      "_dirName": "2",
      "_dirType": "sub",
      "default": {
        "_dirName": "default",
        "_dirType": "uol",
        "_value": "../../default/default"
      }
    },
    "3": {
      "_dirName": "3",
      "_dirType": "sub",
      "default": {
        "_dirName": "default",
        "_dirType": "uol",
        "_value": "../../default/default"
      }
    }
  },
  "walk2": {
    "_dirName": "walk2",
    "_dirType": "sub",
    "0": {
      "_dirName": "0",
      "_dirType": "sub",
      "default": {
        "_dirName": "default",
        "_dirType": "uol",
        "_value": "../../default/default"
      }
    },
    "1": {
      "_dirName": "1",
      "_dirType": "sub",
      "default": {
        "_dirName": "default",
        "_dirType": "uol",
        "_value": "../../default/default"
      }
    },
    "2": {
      "_dirName": "2",
      "_dirType": "sub",
      "default": {
        "_dirName": "default",
        "_dirType": "uol",
        "_value": "../../default/default"
      }
    },
    "3": {
      "_dirName": "3",
      "_dirType": "sub",
      "default": {
        "_dirName": "default",
        "_dirType": "uol",
        "_value": "../../default/default"
      }
    }
  },
  "stand1": {
    "_dirName": "stand1",
    "_dirType": "sub",
    "0": {
      "_dirName": "0",
      "_dirType": "sub",
      "default": {
        "_dirName": "default",
        "_dirType": "uol",
        "_value": "../../default/default"
      }
    },
    "1": {
      "_dirName": "1",
      "_dirType": "sub",
      "default": {
        "_dirName": "default",
        "_dirType": "uol",
        "_value": "../../default/default"
      }
    },
    "2": {
      "_dirName": "2",
      "_dirType": "sub",
      "default": {
        "_dirName": "default",
        "_dirType": "uol",
        "_value": "../../default/default"
      }
    }
  },
  "stand2": {
    "_dirName": "stand2",
    "_dirType": "sub",
    "0": {
      "_dirName": "0",
      "_dirType": "sub",
      "default": {
        "_dirName": "default",
        "_dirType": "uol",
        "_value": "../../default/default"
      }
    },
    "1": {
      "_dirName": "1",
      "_dirType": "sub",
      "default": {
        "_dirName": "default",
        "_dirType": "uol",
        "_value": "../../default/default"
      }
    },
    "2": {
      "_dirName": "2",
      "_dirType": "sub",
      "default": {
        "_dirName": "default",
        "_dirType": "uol",
        "_value": "../../default/default"
      }
    }
  },
  "alert": {
    "_dirName": "alert",
    "_dirType": "sub",
    "0": {
      "_dirName": "0",
      "_dirType": "sub",
      "default": {
        "_dirName": "default",
        "_dirType": "uol",
        "_value": "../../default/default"
      }
    },
    "1": {
      "_dirName": "1",
      "_dirType": "sub",
      "default": {
        "_dirName": "default",
        "_dirType": "uol",
        "_value": "../../default/default"
      }
    },
    "2": {
      "_dirName": "2",
      "_dirType": "sub",
      "default": {
        "_dirName": "default",
        "_dirType": "uol",
        "_value": "../../default/default"
      }
    }
  },
  "swingO1": {
    "_dirName": "swingO1",
    "_dirType": "sub",
    "0": {
      "_dirName": "0",
      "_dirType": "sub",
      "default": {
        "_dirName": "default",
        "_dirType": "uol",
        "_value": "../../default/default"
      }
    },
    "1": {
      "_dirName": "1",
      "_dirType": "sub",
      "default": {
        "_dirName": "default",
        "_dirType": "uol",
        "_value": "../../default/default"
      }
    },
    "2": {
      "_dirName": "2",
      "_dirType": "sub",
      "default": {
        "_dirName": "default",
        "_dirType": "uol",
        "_value": "../../default/default"
      }
    }
  },
  "swingO2": {
    "_dirName": "swingO2",
    "_dirType": "sub",
    "0": {
      "_dirName": "0",
      "_dirType": "sub",
      "default": {
        "_dirName": "default",
        "_dirType": "uol",
        "_value": "../../default/default"
      }
    },
    "1": {
      "_dirName": "1",
      "_dirType": "sub",
      "default": {
        "_dirName": "default",
        "_dirType": "uol",
        "_value": "../../default/default"
      }
    },
    "2": {
      "_dirName": "2",
      "_dirType": "sub",
      "default": {
        "_dirName": "default",
        "_dirType": "uol",
        "_value": "../../default/default"
      }
    }
  },
  "swingO3": {
    "_dirName": "swingO3",
    "_dirType": "sub",
    "0": {
      "_dirName": "0",
      "_dirType": "sub",
      "default": {
        "_dirName": "default",
        "_dirType": "uol",
        "_value": "../../default/default"
      }
    },
    "1": {
      "_dirName": "1",
      "_dirType": "sub",
      "default": {
        "_dirName": "default",
        "_dirType": "uol",
        "_value": "../../default/default"
      }
    },
    "2": {
      "_dirName": "2",
      "_dirType": "sub",
      "default": {
        "_dirName": "default",
        "_dirType": "uol",
        "_value": "../../default/default"
      }
    }
  },
  "swingOF": {
    "_dirName": "swingOF",
    "_dirType": "sub",
    "0": {
      "_dirName": "0",
      "_dirType": "sub",
      "default": {
        "_dirName": "default",
        "_dirType": "uol",
        "_value": "../../default/default"
      }
    },
    "2": {
      "_dirName": "2",
      "_dirType": "sub",
      "default": {
        "_dirName": "default",
        "_dirType": "uol",
        "_value": "../../default/default"
      }
    },
    "3": {
      "_dirName": "3",
      "_dirType": "sub",
      "default": {
        "_dirName": "default",
        "_dirType": "uol",
        "_value": "../../default/default"
      }
    }
  },
  "swingT1": {
    "_dirName": "swingT1",
    "_dirType": "sub",
    "0": {
      "_dirName": "0",
      "_dirType": "sub",
      "default": {
        "_dirName": "default",
        "_dirType": "uol",
        "_value": "../../default/default"
      }
    },
    "1": {
      "_dirName": "1",
      "_dirType": "sub",
      "default": {
        "_dirName": "default",
        "_dirType": "uol",
        "_value": "../../default/default"
      }
    },
    "2": {
      "_dirName": "2",
      "_dirType": "sub",
      "default": {
        "_dirName": "default",
        "_dirType": "uol",
        "_value": "../../default/default"
      }
    }
  },
  "swingT2": {
    "_dirName": "swingT2",
    "_dirType": "sub",
    "0": {
      "_dirName": "0",
      "_dirType": "sub",
      "default": {
        "_dirName": "default",
        "_dirType": "uol",
        "_value": "../../default/default"
      }
    },
    "1": {
      "_dirName": "1",
      "_dirType": "sub",
      "default": {
        "_dirName": "default",
        "_dirType": "uol",
        "_value": "../../default/default"
      }
    },
    "2": {
      "_dirName": "2",
      "_dirType": "sub",
      "default": {
        "_dirName": "default",
        "_dirType": "uol",
        "_value": "../../default/default"
      }
    }
  },
  "swingT3": {
    "_dirName": "swingT3",
    "_dirType": "sub",
    "0": {
      "_dirName": "0",
      "_dirType": "sub",
      "default": {
        "_dirName": "default",
        "_dirType": "uol",
        "_value": "../../default/default"
      }
    },
    "1": {
      "_dirName": "1",
      "_dirType": "sub",
      "default": {
        "_dirName": "default",
        "_dirType": "uol",
        "_value": "../../default/default"
      }
    },
    "2": {
      "_dirName": "2",
      "_dirType": "sub",
      "default": {
        "_dirName": "default",
        "_dirType": "uol",
        "_value": "../../default/default"
      }
    }
  },
  "swingTF": {
    "_dirName": "swingTF",
    "_dirType": "sub",
    "1": {
      "_dirName": "1",
      "_dirType": "sub",
      "default": {
        "_dirName": "default",
        "_dirType": "uol",
        "_value": "../../default/default"
      }
    },
    "2": {
      "_dirName": "2",
      "_dirType": "sub",
      "default": {
        "_dirName": "default",
        "_dirType": "uol",
        "_value": "../../default/default"
      }
    },
    "3": {
      "_dirName": "3",
      "_dirType": "sub",
      "default": {
        "_dirName": "default",
        "_dirType": "uol",
        "_value": "../../default/default"
      }
    }
  },
  "swingP1": {
    "_dirName": "swingP1",
    "_dirType": "sub",
    "0": {
      "_dirName": "0",
      "_dirType": "sub",
      "default": {
        "_dirName": "default",
        "_dirType": "uol",
        "_value": "../../default/default"
      }
    },
    "1": {
      "_dirName": "1",
      "_dirType": "sub",
      "default": {
        "_dirName": "default",
        "_dirType": "uol",
        "_value": "../../default/default"
      }
    },
    "2": {
      "_dirName": "2",
      "_dirType": "sub",
      "default": {
        "_dirName": "default",
        "_dirType": "uol",
        "_value": "../../default/default"
      }
    }
  },
  "swingP2": {
    "_dirName": "swingP2",
    "_dirType": "sub",
    "0": {
      "_dirName": "0",
      "_dirType": "sub",
      "default": {
        "_dirName": "default",
        "_dirType": "uol",
        "_value": "../../default/default"
      }
    },
    "1": {
      "_dirName": "1",
      "_dirType": "sub",
      "default": {
        "_dirName": "default",
        "_dirType": "uol",
        "_value": "../../default/default"
      }
    },
    "2": {
      "_dirName": "2",
      "_dirType": "sub",
      "default": {
        "_dirName": "default",
        "_dirType": "uol",
        "_value": "../../default/default"
      }
    }
  },
  "swingPF": {
    "_dirName": "swingPF",
    "_dirType": "sub",
    "0": {
      "_dirName": "0",
      "_dirType": "sub",
      "default": {
        "_dirName": "default",
        "_dirType": "uol",
        "_value": "../../default/default"
      }
    },
    "1": {
      "_dirName": "1",
      "_dirType": "sub",
      "default": {
        "_dirName": "default",
        "_dirType": "uol",
        "_value": "../../default/default"
      }
    },
    "2": {
      "_dirName": "2",
      "_dirType": "sub",
      "default": {
        "_dirName": "default",
        "_dirType": "uol",
        "_value": "../../default/default"
      }
    },
    "3": {
      "_dirName": "3",
      "_dirType": "sub",
      "default": {
        "_dirName": "default",
        "_dirType": "uol",
        "_value": "../../default/default"
      }
    }
  },
  "stabO1": {
    "_dirName": "stabO1",
    "_dirType": "sub",
    "0": {
      "_dirName": "0",
      "_dirType": "sub",
      "default": {
        "_dirName": "default",
        "_dirType": "uol",
        "_value": "../../default/default"
      }
    },
    "1": {
      "_dirName": "1",
      "_dirType": "sub",
      "default": {
        "_dirName": "default",
        "_dirType": "uol",
        "_value": "../../default/default"
      }
    }
  },
  "stabO2": {
    "_dirName": "stabO2",
    "_dirType": "sub",
    "0": {
      "_dirName": "0",
      "_dirType": "sub",
      "default": {
        "_dirName": "default",
        "_dirType": "uol",
        "_value": "../../default/default"
      }
    },
    "1": {
      "_dirName": "1",
      "_dirType": "sub",
      "default": {
        "_dirName": "default",
        "_dirType": "uol",
        "_value": "../../default/default"
      }
    }
  },
  "stabOF": {
    "_dirName": "stabOF",
    "_dirType": "sub",
    "0": {
      "_dirName": "0",
      "_dirType": "sub",
      "default": {
        "_dirName": "default",
        "_dirType": "uol",
        "_value": "../../default/default"
      }
    },
    "1": {
      "_dirName": "1",
      "_dirType": "sub",
      "default": {
        "_dirName": "default",
        "_dirType": "uol",
        "_value": "../../default/default"
      }
    },
    "2": {
      "_dirName": "2",
      "_dirType": "sub",
      "default": {
        "_dirName": "default",
        "_dirType": "uol",
        "_value": "../../default/default"
      }
    }
  },
  "stabT1": {
    "_dirName": "stabT1",
    "_dirType": "sub",
    "0": {
      "_dirName": "0",
      "_dirType": "sub",
      "default": {
        "_dirName": "default",
        "_dirType": "uol",
        "_value": "../../default/default"
      }
    },
    "1": {
      "_dirName": "1",
      "_dirType": "sub",
      "default": {
        "_dirName": "default",
        "_dirType": "uol",
        "_value": "../../default/default"
      }
    },
    "2": {
      "_dirName": "2",
      "_dirType": "sub",
      "default": {
        "_dirName": "default",
        "_dirType": "uol",
        "_value": "../../default/default"
      }
    }
  },
  "stabT2": {
    "_dirName": "stabT2",
    "_dirType": "sub",
    "0": {
      "_dirName": "0",
      "_dirType": "sub",
      "default": {
        "_dirName": "default",
        "_dirType": "uol",
        "_value": "../../default/default"
      }
    },
    "1": {
      "_dirName": "1",
      "_dirType": "sub",
      "default": {
        "_dirName": "default",
        "_dirType": "uol",
        "_value": "../../default/default"
      }
    },
    "2": {
      "_dirName": "2",
      "_dirType": "sub",
      "default": {
        "_dirName": "default",
        "_dirType": "uol",
        "_value": "../../default/default"
      }
    }
  },
  "stabTF": {
    "_dirName": "stabTF",
    "_dirType": "sub",
    "0": {
      "_dirName": "0",
      "_dirType": "sub",
      "default": {
        "_dirName": "default",
        "_dirType": "uol",
        "_value": "../../default/default"
      }
    },
    "1": {
      "_dirName": "1",
      "_dirType": "sub",
      "default": {
        "_dirName": "default",
        "_dirType": "uol",
        "_value": "../../default/default"
      }
    },
    "2": {
      "_dirName": "2",
      "_dirType": "sub",
      "default": {
        "_dirName": "default",
        "_dirType": "uol",
        "_value": "../../default/default"
      }
    },
    "3": {
      "_dirName": "3",
      "_dirType": "sub",
      "default": {
        "_dirName": "default",
        "_dirType": "uol",
        "_value": "../../default/default"
      }
    }
  },
  "shoot1": {
    "_dirName": "shoot1",
    "_dirType": "sub",
    "0": {
      "_dirName": "0",
      "_dirType": "sub",
      "default": {
        "_dirName": "default",
        "_dirType": "uol",
        "_value": "../../default/default"
      }
    },
    "1": {
      "_dirName": "1",
      "_dirType": "sub",
      "default": {
        "_dirName": "default",
        "_dirType": "uol",
        "_value": "../../default/default"
      }
    },
    "2": {
      "_dirName": "2",
      "_dirType": "sub",
      "default": {
        "_dirName": "default",
        "_dirType": "uol",
        "_value": "../../default/default"
      }
    }
  },
  "shoot2": {
    "_dirName": "shoot2",
    "_dirType": "sub",
    "0": {
      "_dirName": "0",
      "_dirType": "sub",
      "default": {
        "_dirName": "default",
        "_dirType": "uol",
        "_value": "../../default/default"
      }
    },
    "1": {
      "_dirName": "1",
      "_dirType": "sub",
      "default": {
        "_dirName": "default",
        "_dirType": "uol",
        "_value": "../../default/default"
      }
    },
    "2": {
      "_dirName": "2",
      "_dirType": "sub",
      "default": {
        "_dirName": "default",
        "_dirType": "uol",
        "_value": "../../default/default"
      }
    },
    "3": {
      "_dirName": "3",
      "_dirType": "sub",
      "default": {
        "_dirName": "default",
        "_dirType": "uol",
        "_value": "../../default/default"
      }
    },
    "4": {
      "_dirName": "4",
      "_dirType": "sub",
      "default": {
        "_dirName": "default",
        "_dirType": "uol",
        "_value": "../../default/default"
      }
    }
  },
  "shootF": {
    "_dirName": "shootF",
    "_dirType": "sub",
    "0": {
      "_dirName": "0",
      "_dirType": "sub",
      "default": {
        "_dirName": "default",
        "_dirType": "uol",
        "_value": "../../default/default"
      }
    },
    "1": {
      "_dirName": "1",
      "_dirType": "sub",
      "default": {
        "_dirName": "default",
        "_dirType": "uol",
        "_value": "../../default/default"
      }
    },
    "2": {
      "_dirName": "2",
      "_dirType": "sub",
      "default": {
        "_dirName": "default",
        "_dirType": "uol",
        "_value": "../../default/default"
      }
    }
  },
  "proneStab": {
    "_dirName": "proneStab",
    "_dirType": "sub",
    "0": {
      "_dirName": "0",
      "_dirType": "sub",
      "default": {
        "_dirName": "default",
        "_dirType": "uol",
        "_value": "../../default/default"
      }
    },
    "1": {
      "_dirName": "1",
      "_dirType": "sub",
      "default": {
        "_dirName": "default",
        "_dirType": "uol",
        "_value": "../../default/default"
      }
    }
  },
  "prone": {
    "_dirName": "prone",
    "_dirType": "sub",
    "0": {
      "_dirName": "0",
      "_dirType": "sub",
      "default": {
        "_dirName": "default",
        "_dirType": "uol",
        "_value": "../../default/default"
      }
    }
  },
  "heal": {
    "_dirName": "heal",
    "_dirType": "sub",
    "0": {
      "_dirName": "0",
      "_dirType": "sub",
      "default": {
        "_dirName": "default",
        "_dirType": "uol",
        "_value": "../../default/default"
      }
    },
    "1": {
      "_dirName": "1",
      "_dirType": "sub",
      "default": {
        "_dirName": "default",
        "_dirType": "uol",
        "_value": "../../default/default"
      }
    },
    "2": {
      "_dirName": "2",
      "_dirType": "sub",
      "default": {
        "_dirName": "default",
        "_dirType": "uol",
        "_value": "../../default/default"
      }
    }
  },
  "fly": {
    "_dirName": "fly",
    "_dirType": "sub",
    "0": {
      "_dirName": "0",
      "_dirType": "sub",
      "default": {
        "_dirName": "default",
        "_dirType": "uol",
        "_value": "../../default/default"
      }
    },
    "1": {
      "_dirName": "1",
      "_dirType": "sub",
      "default": {
        "_dirName": "default",
        "_dirType": "uol",
        "_value": "../../default/default"
      }
    }
  },
  "jump": {
    "_dirName": "jump",
    "_dirType": "sub",
    "0": {
      "_dirName": "0",
      "_dirType": "sub",
      "default": {
        "_dirName": "default",
        "_dirType": "uol",
        "_value": "../../default/default"
      }
    }
  },
  "sit": {
    "_dirName": "sit",
    "_dirType": "sub",
    "0": {
      "_dirName": "0",
      "_dirType": "sub",
      "default": {
        "_dirName": "default",
        "_dirType": "uol",
        "_value": "../../default/default"
      }
    }
  }
}