{
  "info": {
    "_dirName": "info",
    "_dirType": "sub",
    "bodyAttack": {
      "_dirName": "bodyAttack",
      "_dirType": "Int",
      "_value": 1
    },
    "level": {
      "_dirName": "level",
      "_dirType": "Int",
      "_value": 80
    },
    "maxHP": {
      "_dirName": "maxHP",
      "_dirType": "Int",
      "_value": 120000
    },
    "maxMP": {
      "_dirName": "maxMP",
      "_dirType": "Int",
      "_value": 510
    },
    "speed": {
      "_dirName": "speed",
      "_dirType": "Int",
      "_value": 10
    },
    "PADamage": {
      "_dirName": "PADamage",
      "_dirType": "Int",
      "_value": 260
    },
    "PDDamage": {
      "_dirName": "PDDamage",
      "_dirType": "Int",
      "_value": 260
    },
    "MADamage": {
      "_dirName": "MADamage",
      "_dirType": "Int",
      "_value": 0
    },
    "MDDamage": {
      "_dirName": "MDDamage",
      "_dirType": "Int",
      "_value": 220
    },
    "acc": {
      "_dirName": "acc",
      "_dirType": "Int",
      "_value": 180
    },
    "eva": {
      "_dirName": "eva",
      "_dirType": "Int",
      "_value": 32
    },
    "exp": {
      "_dirName": "exp",
      "_dirType": "Int",
      "_value": 2400
    },
    "undead": {
      "_dirName": "undead",
      "_dirType": "Int",
      "_value": 0
    },
    "pushed": {
      "_dirName": "pushed",
      "_dirType": "Int",
      "_value": 1500
    },
    "fs": {
      "_dirName": "fs",
      "_dirType": "Float",
      "_value": 10
    },
    "summonType": {
      "_dirName": "summonType",
      "_dirType": "Int",
      "_value": 1
    },
    "boss": {
      "_dirName": "boss",
      "_dirType": "Int",
      "_value": 1
    },
    "hpRecovery": {
      "_dirName": "hpRecovery",
      "_dirType": "Int",
      "_value": 100
    },
    "mpRecovery": {
      "_dirName": "mpRecovery",
      "_dirType": "Int",
      "_value": 20
    },
    "link": {
      "_dirName": "link",
      "_dirType": "String",
      "_value": "9001003"
    },
    "skill": {
      "_dirName": "skill",
      "_dirType": "sub",
      "0": {
        "_dirName": "0",
        "_dirType": "sub",
        "skill": {
          "_dirName": "skill",
          "_dirType": "Int",
          "_value": 100
        },
        "action": {
          "_dirName": "action",
          "_dirType": "Int",
          "_value": 1
        },
        "level": {
          "_dirName": "level",
          "_dirType": "Int",
          "_value": 1
        },
        "effectAfter": {
          "_dirName": "effectAfter",
          "_dirType": "Int",
          "_value": 0
        }
      },
      "1": {
        "_dirName": "1",
        "_dirType": "sub",
        "skill": {
          "_dirName": "skill",
          "_dirType": "Int",
          "_value": 102
        },
        "action": {
          "_dirName": "action",
          "_dirType": "Int",
          "_value": 2
        },
        "level": {
          "_dirName": "level",
          "_dirType": "Int",
          "_value": 1
        },
        "effectAfter": {
          "_dirName": "effectAfter",
          "_dirType": "Int",
          "_value": 0
        }
      },
      "2": {
        "_dirName": "2",
        "_dirType": "sub",
        "skill": {
          "_dirName": "skill",
          "_dirType": "Int",
          "_value": 122
        },
        "action": {
          "_dirName": "action",
          "_dirType": "Int",
          "_value": 2
        },
        "level": {
          "_dirName": "level",
          "_dirType": "Int",
          "_value": 2
        },
        "effectAfter": {
          "_dirName": "effectAfter",
          "_dirType": "Int",
          "_value": 0
        }
      }
    },
    "mobType": {
      "_dirName": "mobType",
      "_dirType": "Int",
      "_value": 6
    }
  }
}