{
  "info": {
    "_dirName": "info",
    "_dirType": "sub",
    "bodyAttack": {
      "_dirName": "bodyAttack",
      "_dirType": "Int",
      "_value": 1
    },
    "level": {
      "_dirName": "level",
      "_dirType": "Int",
      "_value": 15
    },
    "maxHP": {
      "_dirName": "maxHP",
      "_dirType": "Int",
      "_value": 400
    },
    "maxMP": {
      "_dirName": "maxMP",
      "_dirType": "Int",
      "_value": 55
    },
    "flySpeed": {
      "_dirName": "flySpeed",
      "_dirType": "Int",
      "_value": -20
    },
    "speed": {
      "_dirName": "speed",
      "_dirType": "Int",
      "_value": -10
    },
    "PADamage": {
      "_dirName": "PADamage",
      "_dirType": "Int",
      "_value": 130
    },
    "PDDamage": {
      "_dirName": "PDDamage",
      "_dirType": "Int",
      "_value": 160
    },
    "MADamage": {
      "_dirName": "MADamage",
      "_dirType": "Int",
      "_value": 150
    },
    "MDDamage": {
      "_dirName": "MDDamage",
      "_dirType": "Int",
      "_value": 180
    },
    "acc": {
      "_dirName": "acc",
      "_dirType": "Int",
      "_value": 190
    },
    "eva": {
      "_dirName": "eva",
      "_dirType": "Int",
      "_value": 20
    },
    "exp": {
      "_dirName": "exp",
      "_dirType": "Int",
      "_value": 102
    },
    "undead": {
      "_dirName": "undead",
      "_dirType": "Int",
      "_value": 0
    },
    "mpRecovery": {
      "_dirName": "mpRecovery",
      "_dirType": "Int",
      "_value": 15
    },
    "pushed": {
      "_dirName": "pushed",
      "_dirType": "Int",
      "_value": 0
    },
    "elemAttr": {
      "_dirName": "elemAttr",
      "_dirType": "String",
      "_value": "L3"
    },
    "fs": {
      "_dirName": "fs",
      "_dirType": "Float",
      "_value": 10
    },
    "summonType": {
      "_dirName": "summonType",
      "_dirType": "Int",
      "_value": 0
    },
    "link": {
      "_dirName": "link",
      "_dirType": "String",
      "_value": "4230117"
    },
    "fixedDamage": {
      "_dirName": "fixedDamage",
      "_dirType": "Int",
      "_value": 5
    }
  }
}